stochasticprocesses/__init__.py
stochasticprocesses/simulation.py
stochasticprocesses-0.15.0.dist-info/METADATA
stochasticprocesses-0.15.0.dist-info/WHEEL
stochasticprocesses-0.15.0.dist-info/top_level.txt
stochasticprocesses-0.15.0.dist-info/RECORD
