Metadata-Version: 2.1
Name: stochasticprocesses
Version: 0.15.0
Summary: A package to simulate stochastic processes
Home-page: https://github.com/JulioCesarMS/StochasticModels.git
Author: Julio César Martínez
Author-email: julio.martinez@gmail.com.mx
License: UNKNOWN
Platform: UNKNOWN
Requires-Python: >= 3.7.3
Requires-Dist: pandas (>=1.0.0)
Requires-Dist: numpy (>=1.15.0)
